wavy_totem_lib/__init__.py
wavy_totem_lib/builder.py
wavy_totem_lib/exceptions.py
wavy_totem_lib/layers.py
wavy_totem_lib/patterns/__init__.py
wavy_totem_lib/patterns/abstract.py
wavy_totem_lib/patterns/soul.py
wavy_totem_lib/patterns/wavy.py
wavy_totem_lib/skin.py
wavy_totem_lib/totem.py
wavy_totem_lib-2.1.2.dist-info/METADATA
wavy_totem_lib-2.1.2.dist-info/WHEEL
wavy_totem_lib-2.1.2.dist-info/licenses/LICENSE
wavy_totem_lib-2.1.2.dist-info/RECORD
