Metadata-Version: 2.4
Name: wavy-totem-lib
Version: 2.1.2
Summary: A library for generating the texture of Minecraft's Totem of Undying
License: BSL-1.0
License-File: LICENSE
Author: WavyCat
Author-email: me@wavycat.ru
Requires-Python: >=3.10,<4.0
Classifier: License :: OSI Approved :: Boost Software License 1.0 (BSL-1.0)
Classifier: Programming Language :: Python :: 3
Classifier: Programming Language :: Python :: 3.10
Classifier: Programming Language :: Python :: 3.11
Classifier: Programming Language :: Python :: 3.12
Classifier: Programming Language :: Python :: 3.13
Classifier: Programming Language :: Python :: 3.14
Requires-Dist: pillow (>=11.0.0,<12.0.0)
Project-URL: Homepage, https://github.com/wavy-cat/wavy-totem-lib
Project-URL: Issue tracker, https://github.com/wavy-cat/wavy-totem-lib/issues
